rectvision/__init__.py
rectvision/data/__init__.py
rectvision/data/converters/__init__.py
rectvision/data/converters/cocoToTfrecords.py
rectvision/data/converters/labelmeToDarknetTxt.py
rectvision/data/converters/labelmeToKerasRetinanetCsv.py
rectvision/data/converters/labelmeToMask.py
rectvision/data/converters/labelmeToTfCsv.py
rectvision/data/converters/labelmeToXml.py
rectvision/data/converters/labelmeToYoloTxt.py
rectvision/data/converters/labelmeToYoloV3KerasTxt.py
rectvision/data/converters/labelmetococo.py
rectvision/data/converters/rectvisConverter.py
rectvision/data/converters/rectvisConverterHelper.py
rectvision/data/converters/xmlToCoco.py
rectvision/data/converters/xmlToDarknetTxt.py
rectvision/data/converters/xmlToJson.py
rectvision/data/converters/xmlToKerasRetinanetCsv.py
rectvision/data/converters/xmlToTfCsv.py
rectvision/data/converters/xmlToYoloTxt.py
rectvision/data/converters/xmlToYoloV3KerasTxt.py
rectvision/models/__init__.py
rectvision/models/yolov5.py
rectvision/settings/__init__.py
rectvision/settings/get_credentials.py
rectvision-3.0.73.dist-info/LICENSE
rectvision-3.0.73.dist-info/METADATA
rectvision-3.0.73.dist-info/WHEEL
rectvision-3.0.73.dist-info/top_level.txt
rectvision-3.0.73.dist-info/RECORD
